Test_CUDA.cp312-win_amd64.pyd
ZTPL/__init__.py
ZTPL/main.py
ZTPL/CUDA/Test.cu
ZTPL-0.1.0.dist-info/METADATA
ZTPL-0.1.0.dist-info/WHEEL
ZTPL-0.1.0.dist-info/top_level.txt
ZTPL-0.1.0.dist-info/RECORD
