Metadata-Version: 2.1
Name: ZTPL
Version: 0.1.0
Summary: ZTPL test with CUDA support
Author: YuningYe
Author-email: 1956860113@qq.com
License: The Unlicense
